[
  {
    "elementType": "geometry",
    "stylers": [
      {
        "color": "#212121"
      }
    ]
  },
  {
    "elementType": "labels.icon",
    "stylers": [
      {
        "visibility": "off"
      }
    ]
  },
  {
    "elementType": "labels.text.fill",
    "stylers": [
      {
        "color": "#757575"
      }
    ]
  },
  {
    "elementType": "labels.text.stroke",
    "stylers": [
      {
        "color": "#212121"
      }
    ]
  },
  {
    "featureType": "administrative",
    "elementType": "geometry",
    "stylers": [
      {
        "color": "#757575"
      }
    ]
  },
  {
    "featureType": "administrative.country",
    "elementType": "geometry.stroke",
    "stylers": [
      {
        "color": "#b71a1a"
      }
    ]
  },
  {
    "featureType": "administrative.country",
    "elementType": "labels.text.fill",
    "stylers": [
      {
        "color": "#9e9e9e"
      }
    ]
  },
  {
    "featureType": "administrative.land_parcel",
    "stylers": [
      {
        "visibility": "off"
      }
    ]
  },
  {
    "featureType": "administrative.locality",
    "elementType": "geometry.stroke",
    "stylers": [
      {
        "color": "#bd5151"
      }
    ]
  },
  {
    "featureType": "administrative.locality",
    "elementType": "labels.text.fill",
    "stylers": [
      {
        "color": "#6a517b"
      }
    ]
  },
  {
    "featureType": "administrative.locality",
    "elementType": "labels.text.stroke",
    "stylers": [
      {
        "color": "#bdbdbd"
      },
      {
        "weight": 0.5
      }
    ]
  },
  {
    "featureType": "poi",
    "elementType": "labels.text.fill",
    "stylers": [
      {
        "color": "#757575"
      }
    ]
  },
  {
    "featureType": "poi.park",
    "elementType": "geometry",
    "stylers": [
      {
        "color": "#181818"
      }
    ]
  },
  {
    "featureType": "poi.park",
    "elementType": "labels.text.fill",
    "stylers": [
      {
        "color": "#616161"
      }
    ]
  },
  {
    "featureType": "poi.park",
    "elementType": "labels.text.stroke",
    "stylers": [
      {
        "color": "#1b1b1b"
      }
    ]
  },
  {
    "featureType": "road",
    "elementType": "geometry.stroke",
    "stylers": [
      {
        "color": "#b71a1a"
      }
    ]
  },
  {
    "featureType": "road",
    "elementType": "labels.text.fill",
    "stylers": [
      {
        "color": "#6d5d98"
      }
    ]
  },
  {
    "featureType": "road.arterial",
    "elementType": "geometry",
    "stylers": [
      {
        "color": "#373737"
      }
    ]
  },
  {
    "featureType": "road.arterial",
    "elementType": "geometry.stroke",
    "stylers": [
      {
        "color": "#b71a1a"
      }
    ]
  },
  {
    "featureType": "road.highway",
    "elementType": "geometry",
    "stylers": [
      {
        "color": "#3c3c3c"
      }
    ]
  },
  {
    "featureType": "road.highway",
    "elementType": "geometry.stroke",
    "stylers": [
      {
        "color": "#b71a1a"
      }
    ]
  },
  {
    "featureType": "road.highway.controlled_access",
    "elementType": "geometry",
    "stylers": [
      {
        "color": "#4e4e4e"
      }
    ]
  },
  {
    "featureType": "road.highway.controlled_access",
    "elementType": "geometry.stroke",
    "stylers": [
      {
        "color": "#b71a1a"
      }
    ]
  },
  {
    "featureType": "road.local",
    "elementType": "geometry.stroke",
    "stylers": [
      {
        "color": "#b71a1a"
      }
    ]
  },
  {
    "featureType": "road.local",
    "elementType": "labels.text.fill",
    "stylers": [
      {
        "color": "#616161"
      }
    ]
  },
  {
    "featureType": "transit",
    "elementType": "labels.text.fill",
    "stylers": [
      {
        "color": "#757575"
      }
    ]
  },
  {
    "featureType": "water",
    "elementType": "geometry",
    "stylers": [
      {
        "color": "#000000"
      }
    ]
  },
  {
    "featureType": "water",
    "elementType": "labels.text.fill",
    "stylers": [
      {
        "color": "#3d3d3d"
      }
    ]
  }
]